[
    {
        "YEAR":"Career",
        "MAT":"174",
        "NO":"28",
        "RUNS":"3942",
        "HS":"114*",
        "AVG":"29.42",
        "BF":"3244",
        "SR":"121.52",
        "100":"1",
        "50":"22",
        "4S":"340",
        "6S":"115",
        "CT":"86",
        "ST":"0"
    },
    {
        "YEAR":"2025",
        "MAT":"3",
        "NO":"1",
        "RUNS":"92",
        "HS":"37",
        "AVG":"46.00",
        "BF":"65",
        "SR":"141.54",
        "100":"0",
        "50":"0",
        "4S":"5",
        "6S":"5",
        "CT":"0",
        "ST":"0"
    },
    {
        "YEAR":"2024",
        "MAT":"1",
        "NO":"0",
        "RUNS":"42",
        "HS":"42",
        "AVG":"42.00",
        "BF":"31",
        "SR":"135.48",
        "100":"0",
        "50":"0",
        "4S":"2",
        "6S":"2",
        "CT":"4",
        "ST":"0"
    },
    {
        "YEAR":"2023",
        "MAT":"10",
        "NO":"0",
        "RUNS":"160",
        "HS":"50",
        "AVG":"17.78",
        "BF":"146",
        "SR":"109.59",
        "100":"0",
        "50":"1",
        "4S":"15",
        "6S":"3",
        "CT":"3",
        "ST":"0"
    },
    {
        "YEAR":"2022",
        "MAT":"6",
        "NO":"0",
        "RUNS":"88",
        "HS":"38",
        "AVG":"14.67",
        "BF":"80",
        "SR":"110.00",
        "100":"0",
        "50":"0",
        "4S":"9",
        "6S":"2",
        "CT":"3",
        "ST":"0"
    },
    {
        "YEAR":"2021",
        "MAT":"8",
        "NO":"2",
        "RUNS":"292",
        "HS":"69*",
        "AVG":"48.66",
        "BF":"236",
        "SR":"123.72",
        "100":"0",
        "50":"3",
        "4S":"21",
        "6S":"10",
        "CT":"5",
        "ST":"0"
    },
    {
        "YEAR":"2020",
        "MAT":"16",
        "NO":"2",
        "RUNS":"425",
        "HS":"83*",
        "AVG":"32.69",
        "BF":"333",
        "SR":"127.62",
        "100":"0",
        "50":"3",
        "4S":"35",
        "6S":"18",
        "CT":"7",
        "ST":"0"
    },
    {
        "YEAR":"2019",
        "MAT":"12",
        "NO":"3",
        "RUNS":"344",
        "HS":"83*",
        "AVG":"43.00",
        "BF":"263",
        "SR":"130.79",
        "100":"0",
        "50":"3",
        "4S":"34",
        "6S":"6",
        "CT":"7",
        "ST":"0"
    },
    {
        "YEAR":"2018",
        "MAT":"15",
        "NO":"2",
        "RUNS":"284",
        "HS":"62*",
        "AVG":"25.81",
        "BF":"246",
        "SR":"115.44",
        "100":"0",
        "50":"3",
        "4S":"22",
        "6S":"5",
        "CT":"9",
        "ST":"0"
    },
    {
        "YEAR":"2017",
        "MAT":"14",
        "NO":"5",
        "RUNS":"396",
        "HS":"81*",
        "AVG":"49.50",
        "BF":"308",
        "SR":"128.57",
        "100":"0",
        "50":"2",
        "4S":"28",
        "6S":"12",
        "CT":"8",
        "ST":"0"
    },
    {
        "YEAR":"2016",
        "MAT":"12",
        "NO":"3",
        "RUNS":"248",
        "HS":"52",
        "AVG":"31.00",
        "BF":"183",
        "SR":"135.51",
        "100":"0",
        "50":"2",
        "4S":"17",
        "6S":"9",
        "CT":"7",
        "ST":"0"
    },
    {
        "YEAR":"2015",
        "MAT":"13",
        "NO":"1",
        "RUNS":"225",
        "HS":"40",
        "AVG":"20.45",
        "BF":"184",
        "SR":"122.28",
        "100":"0",
        "50":"0",
        "4S":"22",
        "6S":"7",
        "CT":"5",
        "ST":"0"
    },
    {
        "YEAR":"2014",
        "MAT":"16",
        "NO":"3",
        "RUNS":"401",
        "HS":"94",
        "AVG":"30.84",
        "BF":"340",
        "SR":"117.94",
        "100":"0",
        "50":"2",
        "4S":"35",
        "6S":"10",
        "CT":"3",
        "ST":"0"
    },
    {
        "YEAR":"2013",
        "MAT":"7",
        "NO":"1",
        "RUNS":"136",
        "HS":"66",
        "AVG":"22.66",
        "BF":"137",
        "SR":"99.27",
        "100":"0",
        "50":"1",
        "4S":"11",
        "6S":"3",
        "CT":"6",
        "ST":"0"
    },
    {
        "YEAR":"2012",
        "MAT":"10",
        "NO":"2",
        "RUNS":"143",
        "HS":"80*",
        "AVG":"20.42",
        "BF":"112",
        "SR":"127.67",
        "100":"0",
        "50":"1",
        "4S":"12",
        "6S":"6",
        "CT":"3",
        "ST":"0"
    },
    {
        "YEAR":"2011",
        "MAT":"10",
        "NO":"0",
        "RUNS":"246",
        "HS":"59",
        "AVG":"27.33",
        "BF":"227",
        "SR":"108.37",
        "100":"0",
        "50":"1",
        "4S":"28",
        "6S":"6",
        "CT":"5",
        "ST":"0"
    },
    {
        "YEAR":"2010",
        "MAT":"13",
        "NO":"1",
        "RUNS":"249",
        "HS":"42*",
        "AVG":"20.75",
        "BF":"226",
        "SR":"110.17",
        "100":"0",
        "50":"0",
        "4S":"27",
        "6S":"7",
        "CT":"7",
        "ST":"0"
    },
    {
        "YEAR":"2009",
        "MAT":"5",
        "NO":"2",
        "RUNS":"168",
        "HS":"114*",
        "AVG":"84.00",
        "BF":"118",
        "SR":"142.37",
        "100":"1",
        "50":"0",
        "4S":"17",
        "6S":"4",
        "CT":"4",
        "ST":"0"
    },
    {
        "YEAR":"2008",
        "MAT":"3",
        "NO":"0",
        "RUNS":"3",
        "HS":"3",
        "AVG":"1.50",
        "BF":"9",
        "SR":"33.33",
        "100":"0",
        "50":"0",
        "4S":"0",
        "6S":"0",
        "CT":"0",
        "ST":"0"
    }
]