[
    {
        "YEAR":"Career",
        "MAT":"15",
        "NO":"2",
        "RUNS":"351",
        "HS":"63",
        "AVG":"27.00",
        "BF":"267",
        "SR":"131.46",
        "100":"0",
        "50":"2",
        "4S":"28",
        "6S":"10",
        "CT":"11",
        "ST":"0"
    },
    {
        "YEAR":"2024",
        "MAT":"13",
        "NO":"2",
        "RUNS":"318",
        "HS":"63",
        "AVG":"28.91",
        "BF":"223",
        "SR":"142.60",
        "100":"0",
        "50":"2",
        "4S":"27",
        "6S":"10",
        "CT":"9",
        "ST":"0"
    },
    {
        "YEAR":"2022",
        "MAT":"2",
        "NO":"0",
        "RUNS":"33",
        "HS":"17",
        "AVG":"16.50",
        "BF":"44",
        "SR":"75.00",
        "100":"0",
        "50":"0",
        "4S":"1",
        "6S":"0",
        "CT":"2",
        "ST":"0"
    }
]