[
    {
        "YEAR":"Career",
        "MAT":"16",
        "BALLS":"333",
        "RUNS":"576",
        "WKTS":"17",
        "BBM":"3\/20",
        "AVE":"33.88",
        "ECON":"10.38",
        "SR":"19.59",
        "4W":"0",
        "5W":"0"
    },
    {
        "YEAR":"2025",
        "MAT":"5",
        "BALLS":"102",
        "RUNS":"181",
        "WKTS":"4",
        "BBM":"2\/44",
        "AVE":"45.25",
        "ECON":"10.65",
        "SR":"25.50",
        "4W":"0",
        "5W":"0"
    },
    {
        "YEAR":"2024",
        "MAT":"4",
        "BALLS":"87",
        "RUNS":"142",
        "WKTS":"4",
        "BBM":"2\/23",
        "AVE":"35.50",
        "ECON":"9.79",
        "SR":"21.75",
        "4W":"0",
        "5W":"0"
    },
    {
        "YEAR":"2023",
        "MAT":"7",
        "BALLS":"144",
        "RUNS":"253",
        "WKTS":"9",
        "BBM":"3\/20",
        "AVE":"28.11",
        "ECON":"10.54",
        "SR":"16.00",
        "4W":"0",
        "5W":"0"
    }
]